otvertka/__init__.py
otvertka/otvertka.py
otvertka-0.1.16.dist-info/METADATA
otvertka-0.1.16.dist-info/WHEEL
otvertka-0.1.16.dist-info/licenses/LICENSE
otvertka-0.1.16.dist-info/RECORD
