Metadata-Version: 2.4
Name: otvertka
Version: 0.1.16
Summary: Набор простых функций для работы с данными
Project-URL: Homepage, https://github.com/stasdikansky/otvertka
Project-URL: Bug Tracker, https://github.com/stasdikansky/otvertka/issues
Author: Stas Dikansky
License: MIT License
License-File: LICENSE
Classifier: License :: OSI Approved :: MIT License
Classifier: Operating System :: OS Independent
Classifier: Programming Language :: Python :: 3
Requires-Python: >=3.7
Requires-Dist: clickhouse-connect>=0.6.8
Requires-Dist: numpy>=1.26.0
Requires-Dist: pandas>=2.0.0
Requires-Dist: pendulum>=2.1.2
Requires-Dist: pingouin>=0.5.3
